midi_tempo_tools/MidiTempoConverter.jar
midi_tempo_tools/__init__.py
midi_tempo_tools/tempo.py
midi_tempo_tools-0.1.0.dist-info/METADATA
midi_tempo_tools-0.1.0.dist-info/WHEEL
midi_tempo_tools-0.1.0.dist-info/top_level.txt
midi_tempo_tools-0.1.0.dist-info/RECORD
