Metadata-Version: 2.1
Name: midi-tempo-tools
Version: 0.1.0
Summary: A tool for handling MIDI file tempo operations
Home-page: https://github.com/zhaoyu010/midiv
Author: Your Name
Author-email: your.email@example.com
Keywords: midi,tempo,music,bpm
Classifier: Development Status :: 3 - Alpha
Classifier: Intended Audience :: Developers
Classifier: Topic :: Multimedia :: Sound/Audio :: MIDI
Classifier: Programming Language :: Python :: 3
Classifier: Programming Language :: Python :: 3.6
Classifier: Programming Language :: Python :: 3.7
Classifier: Programming Language :: Python :: 3.8
Classifier: Programming Language :: Python :: 3.9
Classifier: Programming Language :: Python :: 3.10
Classifier: License :: OSI Approved :: MIT License
Classifier: Operating System :: OS Independent
Requires-Python: >=3.6
Requires-Dist: mido>=1.2.0
